suluvai/__init__.py
suluvai/core/__init__.py
suluvai/core/agent.py
suluvai/core/config.py
suluvai/core/state.py
suluvai/core/subagent.py
suluvai/memory/__init__.py
suluvai/memory/conversation.py
suluvai/memory/working.py
suluvai/storage/__init__.py
suluvai/storage/hybrid.py
suluvai/storage/local.py
suluvai/storage/local_storage.py
suluvai/storage/virtual.py
suluvai/tools/__init__.py
suluvai/tools/filesystem.py
suluvai/tools/planning.py
suluvai/utils/__init__.py
suluvai/utils/stream_agent.py
suluvai/utils/streaming.py
suluvai/utils/tracing.py
suluvai/workflows/__init__.py
suluvai/workflows/base.py
suluvai/workflows/builder.py
suluvai/workflows/conditional.py
suluvai/workflows/custom.py
suluvai/workflows/parallel.py
suluvai/workflows/sequential.py
suluvai-2.1.0.dist-info/licenses/LICENSE
suluvai-2.1.0.dist-info/METADATA
suluvai-2.1.0.dist-info/WHEEL
suluvai-2.1.0.dist-info/top_level.txt
suluvai-2.1.0.dist-info/RECORD
