Metadata-Version: 2.4
Name: suluvai
Version: 2.1.0
Summary: Production-ready AI Agent Framework with LangGraph - Streaming, Storage, Memory & Multi-Agent Support
Author-email: SagaraGlobal <info@sagaraglobal.com>
License: MIT
Project-URL: Homepage, https://github.com/suluvai/suluvai
Project-URL: Documentation, https://github.com/suluvai/suluvai#readme
Project-URL: Repository, https://github.com/suluvai/suluvai
Project-URL: Bug Tracker, https://github.com/suluvai/suluvai/issues
Keywords: langchain,langgraph,agents,ai,llm,streaming,deep-agents,suluvai
Classifier: Development Status :: 4 - Beta
Classifier: Intended Audience :: Developers
Classifier: Topic :: Software Development :: Libraries :: Python Modules
Classifier: Topic :: Scientific/Engineering :: Artificial Intelligence
Classifier: License :: OSI Approved :: MIT License
Classifier: Programming Language :: Python :: 3
Classifier: Programming Language :: Python :: 3.9
Classifier: Programming Language :: Python :: 3.10
Classifier: Programming Language :: Python :: 3.11
Classifier: Programming Language :: Python :: 3.12
Requires-Python: >=3.9
License-File: LICENSE
Requires-Dist: langchain-core>=0.3.0
Requires-Dist: langgraph>=0.2.0
Requires-Dist: pydantic>=2.0.0
Requires-Dist: typing-extensions>=4.0.0
Provides-Extra: dev
Requires-Dist: pytest>=7.0.0; extra == "dev"
Requires-Dist: pytest-asyncio>=0.21.0; extra == "dev"
Requires-Dist: black>=23.0.0; extra == "dev"
Requires-Dist: flake8>=6.0.0; extra == "dev"
Requires-Dist: mypy>=1.0.0; extra == "dev"
Provides-Extra: openai
Requires-Dist: langchain-openai>=0.2.0; extra == "openai"
Requires-Dist: openai>=1.0.0; extra == "openai"
Provides-Extra: anthropic
Requires-Dist: langchain-anthropic>=0.2.0; extra == "anthropic"
Requires-Dist: anthropic>=0.20.0; extra == "anthropic"
Provides-Extra: tracing
Requires-Dist: langsmith>=0.1.0; extra == "tracing"
Dynamic: license-file
